validate_sops/__init__.py
validate_sops/__main__.py
validate_sops/main.py
validate_sops-0.1.2.dist-info/LICENSE
validate_sops-0.1.2.dist-info/METADATA
validate_sops-0.1.2.dist-info/WHEEL
validate_sops-0.1.2.dist-info/entry_points.txt
validate_sops-0.1.2.dist-info/RECORD
