Metadata-Version: 2.3
Name: validate-sops
Version: 0.1.2
Summary: A Python utility to ensure your files are securely encrypted with SOPS. Integrates seamlessly into your pre-commit workflow, providing automated validation for SOPS-encrypted files, enhancing security and compliance in your development process.
License: MIT
Keywords: sops,pre-commit,hook
Author: Vladimir Zhukov
Requires-Python: >=3.11,<4.0
Classifier: License :: OSI Approved :: MIT License
Classifier: Programming Language :: Python :: 3
Classifier: Programming Language :: Python :: 3.11
Classifier: Programming Language :: Python :: 3.12
Classifier: Programming Language :: Python :: 3.13
Requires-Dist: pyyaml (>=6.0.1,<7.0.0)
Project-URL: Homepage, https://github.com/voldy/validate-sops
Project-URL: Repository, https://github.com/voldy/validate-sops
